odoo/addons/stock_storage_type_putaway_abc/README.rst
odoo/addons/stock_storage_type_putaway_abc/__init__.py
odoo/addons/stock_storage_type_putaway_abc/__manifest__.py
odoo/addons/stock_storage_type_putaway_abc/i18n/es_AR.po
odoo/addons/stock_storage_type_putaway_abc/i18n/stock_storage_type_putaway_abc.pot
odoo/addons/stock_storage_type_putaway_abc/models/__init__.py
odoo/addons/stock_storage_type_putaway_abc/models/product_template.py
odoo/addons/stock_storage_type_putaway_abc/models/stock_location.py
odoo/addons/stock_storage_type_putaway_abc/readme/CONTRIBUTORS.rst
odoo/addons/stock_storage_type_putaway_abc/readme/DESCRIPTION.rst
odoo/addons/stock_storage_type_putaway_abc/static/description/icon.png
odoo/addons/stock_storage_type_putaway_abc/static/description/index.html
odoo/addons/stock_storage_type_putaway_abc/tests/__init__.py
odoo/addons/stock_storage_type_putaway_abc/tests/test_abc_location.py
odoo/addons/stock_storage_type_putaway_abc/views/product.xml
odoo/addons/stock_storage_type_putaway_abc/views/stock_location.xml
odoo13_addon_stock_storage_type_putaway_abc-13.0.2.1.0.dist-info/METADATA
odoo13_addon_stock_storage_type_putaway_abc-13.0.2.1.0.dist-info/WHEEL
odoo13_addon_stock_storage_type_putaway_abc-13.0.2.1.0.dist-info/top_level.txt
odoo13_addon_stock_storage_type_putaway_abc-13.0.2.1.0.dist-info/RECORD
