Metadata-Version: 2.1
Name: odoo13-addon-stock-storage-type-putaway-abc
Version: 13.0.2.1.0
Summary: Advanced storage strategy ABC for WMS
Home-page: https://github.com/OCA/wms
Author: Camptocamp, BCIM, Odoo Community Association (OCA)
Author-email: support@odoo-community.org
License: AGPL-3
Platform: UNKNOWN
Classifier: Programming Language :: Python
Classifier: Framework :: Odoo
Classifier: License :: OSI Approved :: GNU Affero General Public License v3
Requires-Python: >=3.5
Requires-Dist: odoo13-addon-stock-storage-type
Requires-Dist: odoo (<13.1dev,>=13.0a)
